{
  "query": "\nSELECT c.id, c.name, c.title, c.company, c.contactTrustTier, c.crmOrphan, c.rejectedAt, cp.projectId,\n  p.name as projectName\nFROM contacts c\nJOIN contactProjects cp ON cp.contactId = c.id\nJOIN projects p ON p.id = cp.projectId\nWHERE cp.projectId IN ('450027','990050','960002','90006','330020','330006','180014')\n  AND c.rejectedAt IS NULL\n  AND c.contactTrustTier = 'send_ready'\n  AND c.crmOrphan = 0\nORDER BY cp.projectId, c.name;\n",
  "command": "mysql --batch --raw --column-names --default-character-set=utf8mb4 --host gateway02.us-east-1.prod.aws.tidbcloud.com --port 4000 --user HWMKhVWm4R1gayY.38561a93bc5c --database 3SMu786VMCWdCnmNSx6pxw --execute \nSELECT c.id, c.name, c.title, c.company, c.contactTrustTier, c.crmOrphan, c.rejectedAt, cp.projectId,\n  p.name as projectName\nFROM contacts c\nJOIN contactProjects cp ON cp.contactId = c.id\nJOIN projects p ON p.id = cp.projectId\nWHERE cp.projectId IN ('450027','990050','960002','90006','330020','330006','180014')\n  AND c.rejectedAt IS NULL\n  AND c.contactTrustTier = 'send_ready'\n  AND c.crmOrphan = 0\nORDER BY cp.projectId, c.name;\n",
  "rows": [
    {
      "id": "1650005",
      "name": "Chris Field",
      "title": "Construction Manager",
      "company": "WaterNSW",
      "contactTrustTier": "send_ready",
      "crmOrphan": "0",
      "rejectedAt": "NULL",
      "projectId": "90006",
      "projectName": "Warragamba Dam Wall Raising"
    },
    {
      "id": "1650002",
      "name": "Mark Coughlin",
      "title": "Construction Manager",
      "company": "WaterNSW",
      "contactTrustTier": "send_ready",
      "crmOrphan": "0",
      "rejectedAt": "NULL",
      "projectId": "90006",
      "projectName": "Warragamba Dam Wall Raising"
    },
    {
      "id": "1650006",
      "name": "Peter Demeo",
      "title": "Construction Manager",
      "company": "WaterNSW",
      "contactTrustTier": "send_ready",
      "crmOrphan": "0",
      "rejectedAt": "NULL",
      "projectId": "90006",
      "projectName": "Warragamba Dam Wall Raising"
    },
    {
      "id": "1650003",
      "name": "Wayne Suttie",
      "title": "Construction Manager",
      "company": "WaterNSW",
      "contactTrustTier": "send_ready",
      "crmOrphan": "0",
      "rejectedAt": "NULL",
      "projectId": "90006",
      "projectName": "Warragamba Dam Wall Raising"
    },
    {
      "id": "570144",
      "name": "Michael Lucas",
      "title": "Procurement Manager @ Yarra Trams | Rolling Stock & Infrastructure Procurement",
      "company": "Yarra Trams",
      "contactTrustTier": "send_ready",
      "crmOrphan": "0",
      "rejectedAt": "NULL",
      "projectId": "180014",
      "projectName": "Melbourne CBD intersection tram system maintenance"
    },
    {
      "id": "570143",
      "name": "Murat Ozdemir",
      "title": "Performance Attribution Manager at Downer",
      "company": "Yarra Trams",
      "contactTrustTier": "send_ready",
      "crmOrphan": "0",
      "rejectedAt": "NULL",
      "projectId": "180014",
      "projectName": "Melbourne CBD intersection tram system maintenance"
    },
    {
      "id": "570146",
      "name": "Sachin Sood",
      "title": "Strategic Procurement Leader",
      "company": "Yarra Trams",
      "contactTrustTier": "send_ready",
      "crmOrphan": "0",
      "rejectedAt": "NULL",
      "projectId": "180014",
      "projectName": "Melbourne CBD intersection tram system maintenance"
    },
    {
      "id": "570141",
      "name": "Sam Grano",
      "title": "Team Manager / Yarra Trams",
      "company": "Yarra Trams",
      "contactTrustTier": "send_ready",
      "crmOrphan": "0",
      "rejectedAt": "NULL",
      "projectId": "180014",
      "projectName": "Melbourne CBD intersection tram system maintenance"
    },
    {
      "id": "780224",
      "name": "Coretta Bessi",
      "title": "Non-Executive Director | Interim Executive | Chief Operations Officer | Chief Procurement Officer | Keynote Speaker",
      "company": "Victorian Government",
      "contactTrustTier": "send_ready",
      "crmOrphan": "0",
      "rejectedAt": "NULL",
      "projectId": "330006",
      "projectName": "Melbourne Airport Rail Link - Jet Fuel Pipeline Relocation"
    },
    {
      "id": "780225",
      "name": "Ernest Stabek",
      "title": "Trusted Advisor, Executive Reality Coach and Strategic Sound Board to many",
      "company": "Victorian Government",
      "contactTrustTier": "send_ready",
      "crmOrphan": "0",
      "rejectedAt": "NULL",
      "projectId": "330006",
      "projectName": "Melbourne Airport Rail Link - Jet Fuel Pipeline Relocation"
    },
    {
      "id": "780226",
      "name": "Fiona Tran-Matesic",
      "title": "Risk Manager at John Holland - Metro Tunnel Project – Rail Network Alliance & Cross Yarra Partnership Packages",
      "company": "John Holland",
      "contactTrustTier": "send_ready",
      "crmOrphan": "0",
      "rejectedAt": "NULL",
      "projectId": "330006",
      "projectName": "Melbourne Airport Rail Link - Jet Fuel Pipeline Relocation"
    },
    {
      "id": "780227",
      "name": "Nick Brockhurst",
      "title": "John Holland",
      "company": "John Holland",
      "contactTrustTier": "send_ready",
      "crmOrphan": "0",
      "rejectedAt": "NULL",
      "projectId": "330006",
      "projectName": "Melbourne Airport Rail Link - Jet Fuel Pipeline Relocation"
    },
    {
      "id": "780270",
      "name": "Ashley Smith",
      "title": "Engineering Team Manager",
      "company": "Sydney Water",
      "contactTrustTier": "send_ready",
      "crmOrphan": "0",
      "rejectedAt": "NULL",
      "projectId": "330020",
      "projectName": "Riverstone Water Resource Recovery Facility Upgrade"
    },
    {
      "id": "780268",
      "name": "Mukul Mahajan",
      "title": "Asset Engineering Manager, Sydney Water",
      "company": "Sydney Water",
      "contactTrustTier": "send_ready",
      "crmOrphan": "0",
      "rejectedAt": "NULL",
      "projectId": "330020",
      "projectName": "Riverstone Water Resource Recovery Facility Upgrade"
    },
    {
      "id": "780271",
      "name": "Trent Olsen",
      "title": "Civil Construction Manager at John Holland",
      "company": "John Holland",
      "contactTrustTier": "send_ready",
      "crmOrphan": "0",
      "rejectedAt": "NULL",
      "projectId": "330020",
      "projectName": "Riverstone Water Resource Recovery Facility Upgrade"
    },
    {
      "id": "780269",
      "name": "Zara Shahraeni",
      "title": "Engineering Team Manager at Sydney Water",
      "company": "Sydney Water",
      "contactTrustTier": "send_ready",
      "crmOrphan": "0",
      "rejectedAt": "NULL",
      "projectId": "330020",
      "projectName": "Riverstone Water Resource Recovery Facility Upgrade"
    },
    {
      "id": "840055",
      "name": "Christopher Hayes",
      "title": "Project Manager at Ausdrill",
      "company": "Ausdrill",
      "contactTrustTier": "send_ready",
      "crmOrphan": "0",
      "rejectedAt": "NULL",
      "projectId": "450027",
      "projectName": "Tunkillia Gold Project"
    },
    {
      "id": "840053",
      "name": "Dair Bakuridze",
      "title": "Project manager",
      "company": "Barton Gold",
      "contactTrustTier": "send_ready",
      "crmOrphan": "0",
      "rejectedAt": "NULL",
      "projectId": "450027",
      "projectName": "Tunkillia Gold Project"
    },
    {
      "id": "1650346",
      "name": "David Wilson",
      "title": "General Manager Projects",
      "company": "Barton Gold",
      "contactTrustTier": "send_ready",
      "crmOrphan": "0",
      "rejectedAt": "NULL",
      "projectId": "450027",
      "projectName": "Tunkillia Gold Project"
    },
    {
      "id": "1650345",
      "name": "Kim Russell",
      "title": "General Manager Development",
      "company": "Barton Gold",
      "contactTrustTier": "send_ready",
      "crmOrphan": "0",
      "rejectedAt": "NULL",
      "projectId": "450027",
      "projectName": "Tunkillia Gold Project"
    },
    {
      "id": "840056",
      "name": "lindsay Lindsay Hall",
      "title": "project manager at Ausdrill",
      "company": "Ausdrill",
      "contactTrustTier": "send_ready",
      "crmOrphan": "0",
      "rejectedAt": "NULL",
      "projectId": "450027",
      "projectName": "Tunkillia Gold Project"
    },
    {
      "id": "840052",
      "name": "Simon Kitson",
      "title": "Project Manager Barton Gold",
      "company": "Barton Gold",
      "contactTrustTier": "send_ready",
      "crmOrphan": "0",
      "rejectedAt": "NULL",
      "projectId": "450027",
      "projectName": "Tunkillia Gold Project"
    },
    {
      "id": "840057",
      "name": "Steven Donhardt",
      "title": "Project Manager at Ausdrill",
      "company": "Ausdrill",
      "contactTrustTier": "send_ready",
      "crmOrphan": "0",
      "rejectedAt": "NULL",
      "projectId": "450027",
      "projectName": "Tunkillia Gold Project"
    },
    {
      "id": "840054",
      "name": "Susan Wilshusen",
      "title": "Writer, entrepreneur with years of client account management experience",
      "company": "Barton Gold",
      "contactTrustTier": "send_ready",
      "crmOrphan": "0",
      "rejectedAt": "NULL",
      "projectId": "450027",
      "projectName": "Tunkillia Gold Project"
    },
    {
      "id": "2100063",
      "name": "Adrian Lim",
      "title": "Project Manager",
      "company": "North East Link Program (VIC)",
      "contactTrustTier": "send_ready",
      "crmOrphan": "0",
      "rejectedAt": "NULL",
      "projectId": "960002",
      "projectName": "North East Link Program"
    },
    {
      "id": "2100060",
      "name": "Brett Kavanagh",
      "title": "Construction Manager",
      "company": "North East Link Program (VIC)",
      "contactTrustTier": "send_ready",
      "crmOrphan": "0",
      "rejectedAt": "NULL",
      "projectId": "960002",
      "projectName": "North East Link Program"
    },
    {
      "id": "2100061",
      "name": "Brett Taig",
      "title": "Digital Engineering Manager",
      "company": "North East Link Program (VIC)",
      "contactTrustTier": "send_ready",
      "crmOrphan": "0",
      "rejectedAt": "NULL",
      "projectId": "960002",
      "projectName": "North East Link Program"
    },
    {
      "id": "2100064",
      "name": "Dheeraj Kandel",
      "title": "Project Manager",
      "company": "North East Link Program (VIC)",
      "contactTrustTier": "send_ready",
      "crmOrphan": "0",
      "rejectedAt": "NULL",
      "projectId": "960002",
      "projectName": "North East Link Program"
    },
    {
      "id": "2100062",
      "name": "Nicholas Mirecki",
      "title": "Project Manager",
      "company": "North East Link Program (VIC)",
      "contactTrustTier": "send_ready",
      "crmOrphan": "0",
      "rejectedAt": "NULL",
      "projectId": "960002",
      "projectName": "North East Link Program"
    },
    {
      "id": "1380039",
      "name": "Darren Whyte",
      "title": "Fleet Manager",
      "company": "Qube",
      "contactTrustTier": "send_ready",
      "crmOrphan": "0",
      "rejectedAt": "NULL",
      "projectId": "990050",
      "projectName": "Bass Strait Decommissioning Infrastructure Upgrade (Barry Beach)"
    },
    {
      "id": "1380038",
      "name": "John Allen",
      "title": "Fleet Manager",
      "company": "Qube",
      "contactTrustTier": "send_ready",
      "crmOrphan": "0",
      "rejectedAt": "NULL",
      "projectId": "990050",
      "projectName": "Bass Strait Decommissioning Infrastructure Upgrade (Barry Beach)"
    },
    {
      "id": "1380040",
      "name": "Sam Leszczynski",
      "title": "General Manager - Mining Services",
      "company": "Qube",
      "contactTrustTier": "send_ready",
      "crmOrphan": "0",
      "rejectedAt": "NULL",
      "projectId": "990050",
      "projectName": "Bass Strait Decommissioning Infrastructure Upgrade (Barry Beach)"
    }
  ],
  "messages": [],
  "stdout": "id\tname\ttitle\tcompany\tcontactTrustTier\tcrmOrphan\trejectedAt\tprojectId\tprojectName\n1650005\tChris Field\tConstruction Manager\tWaterNSW\tsend_ready\t0\tNULL\t90006\tWarragamba Dam Wall Raising\n1650002\tMark Coughlin\tConstruction Manager\tWaterNSW\tsend_ready\t0\tNULL\t90006\tWarragamba Dam Wall Raising\n1650006\tPeter Demeo\tConstruction Manager\tWaterNSW\tsend_ready\t0\tNULL\t90006\tWarragamba Dam Wall Raising\n1650003\tWayne Suttie\tConstruction Manager\tWaterNSW\tsend_ready\t0\tNULL\t90006\tWarragamba Dam Wall Raising\n570144\tMichael Lucas\tProcurement Manager @ Yarra Trams | Rolling Stock & Infrastructure Procurement\tYarra Trams\tsend_ready\t0\tNULL\t180014\tMelbourne CBD intersection tram system maintenance\n570143\tMurat Ozdemir\tPerformance Attribution Manager at Downer\tYarra Trams\tsend_ready\t0\tNULL\t180014\tMelbourne CBD intersection tram system maintenance\n570146\tSachin Sood\tStrategic Procurement Leader\tYarra Trams\tsend_ready\t0\tNULL\t180014\tMelbourne CBD intersection tram system maintenance\n570141\tSam Grano\tTeam Manager / Yarra Trams\tYarra Trams\tsend_ready\t0\tNULL\t180014\tMelbourne CBD intersection tram system maintenance\n780224\tCoretta Bessi\tNon-Executive Director | Interim Executive | Chief Operations Officer | Chief Procurement Officer | Keynote Speaker\tVictorian Government\tsend_ready\t0\tNULL\t330006\tMelbourne Airport Rail Link - Jet Fuel Pipeline Relocation\n780225\tErnest Stabek\tTrusted Advisor, Executive Reality Coach and Strategic Sound Board to many\tVictorian Government\tsend_ready\t0\tNULL\t330006\tMelbourne Airport Rail Link - Jet Fuel Pipeline Relocation\n780226\tFiona Tran-Matesic\tRisk Manager at John Holland - Metro Tunnel Project – Rail Network Alliance & Cross Yarra Partnership Packages\tJohn Holland\tsend_ready\t0\tNULL\t330006\tMelbourne Airport Rail Link - Jet Fuel Pipeline Relocation\n780227\tNick Brockhurst\tJohn Holland\tJohn Holland\tsend_ready\t0\tNULL\t330006\tMelbourne Airport Rail Link - Jet Fuel Pipeline Relocation\n780270\tAshley Smith\tEngineering Team Manager\tSydney Water\tsend_ready\t0\tNULL\t330020\tRiverstone Water Resource Recovery Facility Upgrade\n780268\tMukul Mahajan\tAsset Engineering Manager, Sydney Water\tSydney Water\tsend_ready\t0\tNULL\t330020\tRiverstone Water Resource Recovery Facility Upgrade\n780271\tTrent Olsen\tCivil Construction Manager at John Holland\tJohn Holland\tsend_ready\t0\tNULL\t330020\tRiverstone Water Resource Recovery Facility Upgrade\n780269\tZara Shahraeni\tEngineering Team Manager at Sydney Water\tSydney Water\tsend_ready\t0\tNULL\t330020\tRiverstone Water Resource Recovery Facility Upgrade\n840055\tChristopher Hayes\tProject Manager at Ausdrill\tAusdrill\tsend_ready\t0\tNULL\t450027\tTunkillia Gold Project\n840053\tDair Bakuridze\tProject manager\tBarton Gold\tsend_ready\t0\tNULL\t450027\tTunkillia Gold Project\n1650346\tDavid Wilson\tGeneral Manager Projects\tBarton Gold\tsend_ready\t0\tNULL\t450027\tTunkillia Gold Project\n1650345\tKim Russell\tGeneral Manager Development\tBarton Gold\tsend_ready\t0\tNULL\t450027\tTunkillia Gold Project\n840056\tlindsay Lindsay Hall\tproject manager at Ausdrill\tAusdrill\tsend_ready\t0\tNULL\t450027\tTunkillia Gold Project\n840052\tSimon Kitson\tProject Manager Barton Gold\tBarton Gold\tsend_ready\t0\tNULL\t450027\tTunkillia Gold Project\n840057\tSteven Donhardt\tProject Manager at Ausdrill\tAusdrill\tsend_ready\t0\tNULL\t450027\tTunkillia Gold Project\n840054\tSusan Wilshusen\tWriter, entrepreneur with years of client account management experience\tBarton Gold\tsend_ready\t0\tNULL\t450027\tTunkillia Gold Project\n2100063\tAdrian Lim\tProject Manager\tNorth East Link Program (VIC)\tsend_ready\t0\tNULL\t960002\tNorth East Link Program\n2100060\tBrett Kavanagh\tConstruction Manager\tNorth East Link Program (VIC)\tsend_ready\t0\tNULL\t960002\tNorth East Link Program\n2100061\tBrett Taig\tDigital Engineering Manager\tNorth East Link Program (VIC)\tsend_ready\t0\tNULL\t960002\tNorth East Link Program\n2100064\tDheeraj Kandel\tProject Manager\tNorth East Link Program (VIC)\tsend_ready\t0\tNULL\t960002\tNorth East Link Program\n2100062\tNicholas Mirecki\tProject Manager\tNorth East Link Program (VIC)\tsend_ready\t0\tNULL\t960002\tNorth East Link Program\n1380039\tDarren Whyte\tFleet Manager\tQube\tsend_ready\t0\tNULL\t990050\tBass Strait Decommissioning Infrastructure Upgrade (Barry Beach)\n1380038\tJohn Allen\tFleet Manager\tQube\tsend_ready\t0\tNULL\t990050\tBass Strait Decommissioning Infrastructure Upgrade (Barry Beach)\n1380040\tSam Leszczynski\tGeneral Manager - Mining Services\tQube\tsend_ready\t0\tNULL\t990050\tBass Strait Decommissioning Infrastructure Upgrade (Barry Beach)\n",
  "stderr": "",
  "execution_time_ms": 1982
}