{
  "query": "\nSELECT \n  u.name AS rep_name,\n  p.id AS project_id,\n  p.name AS project_name,\n  p.priority,\n  p.location,\n  p.value,\n  p.stage,\n  p.actionTier,\n  p.owner,\n  p.sector,\n  p.suppressed,\n  p.discoveryStatus,\n  p.lastDiscoveryAt,\n  p.discoveryAttempts\nFROM users u\nJOIN userProfiles up ON up.userId = u.id\nJOIN projects p ON (\n  p.priority IN ('hot', 'warm')\n  AND p.suppressed = 0\n  AND (\n    JSON_CONTAINS(up.territories, JSON_QUOTE(p.location), '$')\n    OR JSON_CONTAINS(up.territories, '\"NATIONAL\"', '$')\n    OR JSON_CONTAINS(up.territories, '\"National\"', '$')\n  )\n)\nWHERE u.name IN ('Ryan Pemberton', 'Brett Hansen', 'Daniel Zec', 'Dan Day', 'Amit Bhargava', 'Leo Williams ')\n  AND u.role = 'user'\n  AND p.actionTier IN ('tier1_actionable', 'tier2_warm')\nORDER BY u.name, p.priority DESC, p.actionTier ASC\nLIMIT 60;\n",
  "command": "mysql --batch --raw --column-names --default-character-set=utf8mb4 --host gateway02.us-east-1.prod.aws.tidbcloud.com --port 4000 --user HWMKhVWm4R1gayY.38561a93bc5c --database 3SMu786VMCWdCnmNSx6pxw --execute \nSELECT \n  u.name AS rep_name,\n  p.id AS project_id,\n  p.name AS project_name,\n  p.priority,\n  p.location,\n  p.value,\n  p.stage,\n  p.actionTier,\n  p.owner,\n  p.sector,\n  p.suppressed,\n  p.discoveryStatus,\n  p.lastDiscoveryAt,\n  p.discoveryAttempts\nFROM users u\nJOIN userProfiles up ON up.userId = u.id\nJOIN projects p ON (\n  p.priority IN ('hot', 'warm')\n  AND p.suppressed = 0\n  AND (\n    JSON_CONTAINS(up.territories, JSON_QUOTE(p.location), '$')\n    OR JSON_CONTAINS(up.territories, '\"NATIONAL\"', '$')\n    OR JSON_CONTAINS(up.territories, '\"National\"', '$')\n  )\n)\nWHERE u.name IN ('Ryan Pemberton', 'Brett Hansen', 'Daniel Zec', 'Dan Day', 'Amit Bhargava', 'Leo Williams ')\n  AND u.role = 'user'\n  AND p.actionTier IN ('tier1_actionable', 'tier2_warm')\nORDER BY u.name, p.priority DESC, p.actionTier ASC\nLIMIT 60;\n",
  "rows": [
    {
      "rep_name": "Amit Bhargava",
      "project_id": "120003",
      "project_name": "RAAF Base Tindal Redevelopment Stage 6",
      "priority": "warm",
      "location": "NT",
      "value": "$1.1 billion",
      "stage": "Active — 0 open, 25 awarded, 2 closed work packages",
      "actionTier": "tier1_actionable",
      "owner": "Lendlease Construction Pty Limited",
      "sector": "defence",
      "suppressed": "0",
      "discoveryStatus": "discovery_queued",
      "lastDiscoveryAt": "2026-05-03 04:04:35",
      "discoveryAttempts": "0"
    },
    {
      "rep_name": "Amit Bhargava",
      "project_id": "1200024",
      "project_name": "WA ferry infrastructure expansion",
      "priority": "warm",
      "location": "WA",
      "value": "Unknown",
      "stage": "Approvals secured, moving toward procurement phase",
      "actionTier": "tier1_actionable",
      "owner": "Unknown",
      "sector": "infrastructure",
      "suppressed": "0",
      "discoveryStatus": "no_contacts",
      "lastDiscoveryAt": "NULL",
      "discoveryAttempts": "0"
    },
    {
      "rep_name": "Amit Bhargava",
      "project_id": "120008",
      "project_name": "Woodside NWS Subsea Tieback Program",
      "priority": "warm",
      "location": "WA",
      "value": "$5+ billion",
      "stage": "Active — 0 open, 10 awarded, 1 closed work packages",
      "actionTier": "tier1_actionable",
      "owner": "Woodside Energy Ltd",
      "sector": "oil_gas",
      "suppressed": "0",
      "discoveryStatus": "send_ready_contact",
      "lastDiscoveryAt": "NULL",
      "discoveryAttempts": "0"
    },
    {
      "rep_name": "Amit Bhargava",
      "project_id": "30006",
      "project_name": "NSW LDES Tender Projects (Six Projects)",
      "priority": "warm",
      "location": "NSW",
      "value": "Unknown",
      "stage": "Contracts awarded",
      "actionTier": "tier1_actionable",
      "owner": "NSW Government (via ASL/AEMO Services) contracting six new battery storage projects",
      "sector": "energy",
      "suppressed": "0",
      "discoveryStatus": "discovery_queued",
      "lastDiscoveryAt": "NULL",
      "discoveryAttempts": "0"
    },
    {
      "rep_name": "Amit Bhargava",
      "project_id": "270014",
      "project_name": "Queensland road upgrade",
      "priority": "warm",
      "location": "QLD",
      "value": "Unknown",
      "stage": "Advancing toward 2027 construction",
      "actionTier": "tier1_actionable",
      "owner": "Unknown",
      "sector": "infrastructure",
      "suppressed": "0",
      "discoveryStatus": "discovery_queued",
      "lastDiscoveryAt": "NULL",
      "discoveryAttempts": "0"
    },
    {
      "rep_name": "Amit Bhargava",
      "project_id": "720010",
      "project_name": "Victorian gas import terminal",
      "priority": "warm",
      "location": "VIC",
      "value": "Unknown",
      "stage": "Environmental approval secured, moving toward construction",
      "actionTier": "tier1_actionable",
      "owner": "Unknown",
      "sector": "energy",
      "suppressed": "0",
      "discoveryStatus": "discovery_queued",
      "lastDiscoveryAt": "2026-05-03 04:04:35",
      "discoveryAttempts": "0"
    },
    {
      "rep_name": "Amit Bhargava",
      "project_id": "630007",
      "project_name": "Victoria Grid Upgrades and Water Infrastructure",
      "priority": "warm",
      "location": "VIC",
      "value": "Undisclosed",
      "stage": "Ongoing upgrades",
      "actionTier": "tier1_actionable",
      "owner": "Victorian Utilities (implied)",
      "sector": "energy",
      "suppressed": "0",
      "discoveryStatus": "send_ready_contact",
      "lastDiscoveryAt": "2026-05-07 07:43:18",
      "discoveryAttempts": "1"
    },
    {
      "rep_name": "Amit Bhargava",
      "project_id": "450010",
      "project_name": "ACT Government Open Tenders (various projects)",
      "priority": "warm",
      "location": "ACT",
      "value": "Unspecified",
      "stage": "Open Request for Tender (RFT)",
      "actionTier": "tier1_actionable",
      "owner": "ACT Government",
      "sector": "infrastructure",
      "suppressed": "0",
      "discoveryStatus": "named_contact_no_email",
      "lastDiscoveryAt": "2026-05-08 01:46:52",
      "discoveryAttempts": "2"
    },
    {
      "rep_name": "Amit Bhargava",
      "project_id": "120028",
      "project_name": "Ebor Battery Storage System",
      "priority": "warm",
      "location": "NSW",
      "value": "100 MW / 870 MWh",
      "stage": "Tender awarded (Long-Term Energy Service Agreement)",
      "actionTier": "tier1_actionable",
      "owner": "Energy Vault, Bridge Energy",
      "sector": "energy",
      "suppressed": "0",
      "discoveryStatus": "discovery_queued",
      "lastDiscoveryAt": "NULL",
      "discoveryAttempts": "0"
    },
    {
      "rep_name": "Amit Bhargava",
      "project_id": "150019",
      "project_name": "New South Wales 12GWh Long Duration Energy Storage (LDES) Tender",
      "priority": "warm",
      "location": "NSW",
      "value": "Unknown",
      "stage": "Tender process (discussion)",
      "actionTier": "tier1_actionable",
      "owner": "NSW Government (via tender process)",
      "sector": "energy",
      "suppressed": "0",
      "discoveryStatus": "discovery_queued",
      "lastDiscoveryAt": "NULL",
      "discoveryAttempts": "0"
    },
    {
      "rep_name": "Amit Bhargava",
      "project_id": "240011",
      "project_name": "Dinawan Solar Farm",
      "priority": "warm",
      "location": "NSW",
      "value": "Unknown (part of $34 billion total for 14 projects)",
      "stage": "EOI endorsement / Planning",
      "actionTier": "tier1_actionable",
      "owner": "Unknown",
      "sector": "energy",
      "suppressed": "0",
      "discoveryStatus": "discovery_queued",
      "lastDiscoveryAt": "NULL",
      "discoveryAttempts": "0"
    },
    {
      "rep_name": "Amit Bhargava",
      "project_id": "120025",
      "project_name": "Kingswood Battery Energy Storage System (BESS)",
      "priority": "warm",
      "location": "NSW",
      "value": "Unknown",
      "stage": "Long-term contract awarded, development ongoing",
      "actionTier": "tier1_actionable",
      "owner": "Iberdrola Australia",
      "sector": "energy",
      "suppressed": "0",
      "discoveryStatus": "discovery_queued",
      "lastDiscoveryAt": "NULL",
      "discoveryAttempts": "0"
    },
    {
      "rep_name": "Amit Bhargava",
      "project_id": "120040",
      "project_name": "Midland Highway Lake Leake Junction Upgrade (4189)",
      "priority": "warm",
      "location": "TAS",
      "value": "Unknown",
      "stage": "Open tender",
      "actionTier": "tier1_actionable",
      "owner": "Tasmanian Government",
      "sector": "infrastructure",
      "suppressed": "0",
      "discoveryStatus": "discovery_queued",
      "lastDiscoveryAt": "NULL",
      "discoveryAttempts": "0"
    },
    {
      "rep_name": "Amit Bhargava",
      "project_id": "750007",
      "project_name": "First giant turbine parts for the only wind farm under construction in NSW to begin long road journey soon",
      "priority": "warm",
      "location": "NSW",
      "value": "Unknown",
      "stage": "Construction (turbine delivery)",
      "actionTier": "tier1_actionable",
      "owner": "Unknown",
      "sector": "energy",
      "suppressed": "0",
      "discoveryStatus": "blocked_dirty_owner",
      "lastDiscoveryAt": "2026-05-07 07:38:16",
      "discoveryAttempts": "1"
    },
    {
      "rep_name": "Amit Bhargava",
      "project_id": "450008",
      "project_name": "ACT Government Open Tenders (RFT-002)",
      "priority": "warm",
      "location": "ACT",
      "value": "Unknown",
      "stage": "Tender Open",
      "actionTier": "tier1_actionable",
      "owner": "ACT Government",
      "sector": "infrastructure",
      "suppressed": "0",
      "discoveryStatus": "named_contact_no_email",
      "lastDiscoveryAt": "2026-05-08 01:46:54",
      "discoveryAttempts": "2"
    },
    {
      "rep_name": "Amit Bhargava",
      "project_id": "120023",
      "project_name": "NSW Long Duration Storage Tender Round 6 Projects",
      "priority": "warm",
      "location": "NSW",
      "value": "Unknown",
      "stage": "Contracts awarded, planning/development to commence",
      "actionTier": "tier1_actionable",
      "owner": "Various (awarded by NSW Government)",
      "sector": "energy",
      "suppressed": "0",
      "discoveryStatus": "discovery_queued",
      "lastDiscoveryAt": "NULL",
      "discoveryAttempts": "0"
    },
    {
      "rep_name": "Amit Bhargava",
      "project_id": "120007",
      "project_name": "Chevron Australia Operations — NWS & Gorgon",
      "priority": "warm",
      "location": "WA",
      "value": "$54 billion (Gorgon project value)",
      "stage": "Active — 0 open, 92 awarded, 38 closed work packages",
      "actionTier": "tier1_actionable",
      "owner": "Chevron Australia Pty Ltd",
      "sector": "oil_gas",
      "suppressed": "0",
      "discoveryStatus": "send_ready_contact",
      "lastDiscoveryAt": "NULL",
      "discoveryAttempts": "0"
    },
    {
      "rep_name": "Amit Bhargava",
      "project_id": "150009",
      "project_name": "Major battery storage project in Victoria",
      "priority": "warm",
      "location": "VIC",
      "value": "Unknown",
      "stage": "Accelerated planning approval",
      "actionTier": "tier2_warm",
      "owner": "Unknown",
      "sector": "energy",
      "suppressed": "0",
      "discoveryStatus": "blocked_dirty_owner",
      "lastDiscoveryAt": "NULL",
      "discoveryAttempts": "0"
    },
    {
      "rep_name": "Amit Bhargava",
      "project_id": "270005",
      "project_name": "Australian Silicon Ingot and Wafer Manufacturing Facility",
      "priority": "warm",
      "location": "QLD",
      "value": "Unknown",
      "stage": "Planning/Approval - Major Project Status",
      "actionTier": "tier2_warm",
      "owner": "Unknown",
      "sector": "energy",
      "suppressed": "0",
      "discoveryStatus": "blocked_dirty_owner",
      "lastDiscoveryAt": "NULL",
      "discoveryAttempts": "0"
    },
    {
      "rep_name": "Amit Bhargava",
      "project_id": "120046",
      "project_name": "Tonic Group 440MWh Solar-plus-Storage Facility",
      "priority": "warm",
      "location": "WA",
      "value": "Unknown",
      "stage": "Environmental approval received",
      "actionTier": "tier2_warm",
      "owner": "Tonic Group",
      "sector": "energy",
      "suppressed": "0",
      "discoveryStatus": "no_contacts",
      "lastDiscoveryAt": "NULL",
      "discoveryAttempts": "0"
    },
    {
      "rep_name": "Amit Bhargava",
      "project_id": "90019",
      "project_name": "Capricornia Energy Hub — Pumped Hydro",
      "priority": "warm",
      "location": "QLD",
      "value": "750 MW (Pumped Storage)",
      "stage": "Proposed",
      "actionTier": "tier2_warm",
      "owner": "Copenhagen Infrastructure Partners",
      "sector": "energy",
      "suppressed": "0",
      "discoveryStatus": "no_contacts",
      "lastDiscoveryAt": "NULL",
      "discoveryAttempts": "0"
    },
    {
      "rep_name": "Amit Bhargava",
      "project_id": "510017",
      "project_name": "Transgrid 2GW Grid Battery Storage Shortlist",
      "priority": "warm",
      "location": "NSW",
      "value": "Unknown",
      "stage": "Shortlisting/Planning",
      "actionTier": "tier2_warm",
      "owner": "Transgrid",
      "sector": "energy",
      "suppressed": "0",
      "discoveryStatus": "no_contacts",
      "lastDiscoveryAt": "NULL",
      "discoveryAttempts": "0"
    },
    {
      "rep_name": "Amit Bhargava",
      "project_id": "720014",
      "project_name": "Sundown Energy Park",
      "priority": "warm",
      "location": "QLD",
      "value": "Unknown",
      "stage": "Grid connection approval received",
      "actionTier": "tier2_warm",
      "owner": "Recurrent Energy Australia",
      "sector": "energy",
      "suppressed": "0",
      "discoveryStatus": "no_contacts",
      "lastDiscoveryAt": "NULL",
      "discoveryAttempts": "0"
    },
    {
      "rep_name": "Amit Bhargava",
      "project_id": "30007",
      "project_name": "Octopus Australia 4.8GWh BESS Project",
      "priority": "warm",
      "location": "NSW",
      "value": "Unknown",
      "stage": "Acquired, planning to develop",
      "actionTier": "tier2_warm",
      "owner": "Octopus Australia",
      "sector": "energy",
      "suppressed": "0",
      "discoveryStatus": "no_contacts",
      "lastDiscoveryAt": "NULL",
      "discoveryAttempts": "0"
    },
    {
      "rep_name": "Amit Bhargava",
      "project_id": "480062",
      "project_name": "Sandy Mitchell Rare Earths Project",
      "priority": "warm",
      "location": "QLD",
      "value": "Unknown",
      "stage": "Secured mining licence",
      "actionTier": "tier2_warm",
      "owner": "Ark Mines",
      "sector": "mining",
      "suppressed": "0",
      "discoveryStatus": "no_contacts",
      "lastDiscoveryAt": "NULL",
      "discoveryAttempts": "0"
    },
    {
      "rep_name": "Amit Bhargava",
      "project_id": "90021",
      "project_name": "Cobbora Solar Farm",
      "priority": "warm",
      "location": "NSW",
      "value": "1,100 MW (Solar 700 + BESS 400)",
      "stage": "Proposed",
      "actionTier": "tier2_warm",
      "owner": "Pacific Partnerships",
      "sector": "energy",
      "suppressed": "0",
      "discoveryStatus": "no_contacts",
      "lastDiscoveryAt": "NULL",
      "discoveryAttempts": "0"
    },
    {
      "rep_name": "Amit Bhargava",
      "project_id": "750008",
      "project_name": "Ausgrid's Energy Storage as a Service offer and network batteries",
      "priority": "warm",
      "location": "NSW",
      "value": "Unknown",
      "stage": "Planning/Development (service offering)",
      "actionTier": "tier2_warm",
      "owner": "Ausgrid",
      "sector": "energy",
      "suppressed": "0",
      "discoveryStatus": "send_ready_contact",
      "lastDiscoveryAt": "NULL",
      "discoveryAttempts": "0"
    },
    {
      "rep_name": "Amit Bhargava",
      "project_id": "1200052",
      "project_name": "WA Advanced Manufacturing Facilities for Housing",
      "priority": "warm",
      "location": "WA",
      "value": "48 million AUD",
      "stage": "Funding Announced",
      "actionTier": "tier2_warm",
      "owner": "Western Australian Government",
      "sector": "infrastructure",
      "suppressed": "0",
      "discoveryStatus": "discovery_queued",
      "lastDiscoveryAt": "NULL",
      "discoveryAttempts": "0"
    },
    {
      "rep_name": "Amit Bhargava",
      "project_id": "90023",
      "project_name": "Hexham Wind Farm",
      "priority": "warm",
      "location": "VIC",
      "value": "686 MW (Wind)",
      "stage": "Proposed",
      "actionTier": "tier2_warm",
      "owner": "Wind Prospect Pty Ltd",
      "sector": "energy",
      "suppressed": "0",
      "discoveryStatus": "no_contacts",
      "lastDiscoveryAt": "NULL",
      "discoveryAttempts": "0"
    },
    {
      "rep_name": "Amit Bhargava",
      "project_id": "300025",
      "project_name": "Queensland Big Battery Project (Unnamed)",
      "priority": "warm",
      "location": "QLD",
      "value": "Unknown",
      "stage": "Planning/Approval (called in by LNP)",
      "actionTier": "tier2_warm",
      "owner": "Unknown (LNP government called in)",
      "sector": "energy",
      "suppressed": "0",
      "discoveryStatus": "blocked_dirty_owner",
      "lastDiscoveryAt": "NULL",
      "discoveryAttempts": "0"
    },
    {
      "rep_name": "Amit Bhargava",
      "project_id": "90022",
      "project_name": "Spicers Creek Wind Farm",
      "priority": "warm",
      "location": "NSW",
      "value": "702 MW (Wind)",
      "stage": "Proposed",
      "actionTier": "tier2_warm",
      "owner": "Squadron Energy",
      "sector": "energy",
      "suppressed": "0",
      "discoveryStatus": "no_contacts",
      "lastDiscoveryAt": "NULL",
      "discoveryAttempts": "0"
    },
    {
      "rep_name": "Amit Bhargava",
      "project_id": "90013",
      "project_name": "Liverpool Range Wind Farm",
      "priority": "warm",
      "location": "NSW",
      "value": "1,332 MW (Wind)",
      "stage": "Proposed",
      "actionTier": "tier2_warm",
      "owner": "Tilt Renewables",
      "sector": "energy",
      "suppressed": "0",
      "discoveryStatus": "no_contacts",
      "lastDiscoveryAt": "NULL",
      "discoveryAttempts": "0"
    },
    {
      "rep_name": "Amit Bhargava",
      "project_id": "90025",
      "project_name": "Richmond Valley Solar and BESS",
      "priority": "warm",
      "location": "NSW",
      "value": "775 MW (Solar 500 + BESS 275)",
      "stage": "Proposed",
      "actionTier": "tier2_warm",
      "owner": "Ark Energy",
      "sector": "energy",
      "suppressed": "0",
      "discoveryStatus": "no_contacts",
      "lastDiscoveryAt": "NULL",
      "discoveryAttempts": "0"
    },
    {
      "rep_name": "Amit Bhargava",
      "project_id": "90027",
      "project_name": "Bashan Wind Farm",
      "priority": "warm",
      "location": "TAS",
      "value": "460 MW (Wind)",
      "stage": "Proposed",
      "actionTier": "tier2_warm",
      "owner": "Bashan Wind Farm Pty Ltd",
      "sector": "energy",
      "suppressed": "0",
      "discoveryStatus": "no_contacts",
      "lastDiscoveryAt": "NULL",
      "discoveryAttempts": "0"
    },
    {
      "rep_name": "Amit Bhargava",
      "project_id": "990018",
      "project_name": "Tasmanian Transmission Infrastructure Delivery",
      "priority": "warm",
      "location": "TAS",
      "value": "Unknown",
      "stage": "Moving into delivery readiness following environmental approval",
      "actionTier": "tier2_warm",
      "owner": "Unknown",
      "sector": "energy",
      "suppressed": "0",
      "discoveryStatus": "discovery_queued",
      "lastDiscoveryAt": "NULL",
      "discoveryAttempts": "0"
    },
    {
      "rep_name": "Amit Bhargava",
      "project_id": "120033",
      "project_name": "Esmeralda Graphite Mine Project",
      "priority": "warm",
      "location": "QLD",
      "value": "$1.3 billion",
      "stage": "Proposed project, collaboration for supply chain",
      "actionTier": "tier2_warm",
      "owner": "Graphinex",
      "sector": "mining",
      "suppressed": "0",
      "discoveryStatus": "no_contacts",
      "lastDiscoveryAt": "NULL",
      "discoveryAttempts": "0"
    },
    {
      "rep_name": "Amit Bhargava",
      "project_id": "90017",
      "project_name": "Bundey BESS and Solar Project",
      "priority": "warm",
      "location": "SA",
      "value": "2,100 MW (Solar 900 + BESS 1200)",
      "stage": "Proposed",
      "actionTier": "tier2_warm",
      "owner": "Genaspi Energy Group",
      "sector": "energy",
      "suppressed": "0",
      "discoveryStatus": "no_contacts",
      "lastDiscoveryAt": "NULL",
      "discoveryAttempts": "0"
    },
    {
      "rep_name": "Amit Bhargava",
      "project_id": "210001",
      "project_name": "Federal and SA Government Housing Deal",
      "priority": "warm",
      "location": "SA",
      "value": "$801.5 million",
      "stage": "Funding announced",
      "actionTier": "tier2_warm",
      "owner": "Federal Government and South Australian Government",
      "sector": "infrastructure",
      "suppressed": "0",
      "discoveryStatus": "blocked_government_owner",
      "lastDiscoveryAt": "NULL",
      "discoveryAttempts": "0"
    },
    {
      "rep_name": "Amit Bhargava",
      "project_id": "990032",
      "project_name": "Van Uden Heap Leach Gold Project",
      "priority": "warm",
      "location": "WA",
      "value": "Unknown",
      "stage": "Feasibility Study / FID eyed for Q3 2026",
      "actionTier": "tier2_warm",
      "owner": "TG Metals",
      "sector": "mining",
      "suppressed": "0",
      "discoveryStatus": "discovery_queued",
      "lastDiscoveryAt": "NULL",
      "discoveryAttempts": "0"
    },
    {
      "rep_name": "Amit Bhargava",
      "project_id": "30011",
      "project_name": "Victoria Government Development Facilitation Program BESS Projects",
      "priority": "warm",
      "location": "VIC",
      "value": "Unknown",
      "stage": "Approved",
      "actionTier": "tier2_warm",
      "owner": "Victoria Government",
      "sector": "energy",
      "suppressed": "0",
      "discoveryStatus": "blocked_government_owner",
      "lastDiscoveryAt": "NULL",
      "discoveryAttempts": "0"
    },
    {
      "rep_name": "Amit Bhargava",
      "project_id": "210030",
      "project_name": "EnergyConnect Interconnector",
      "priority": "warm",
      "location": "NSW",
      "value": "Unknown",
      "stage": "Underway, facing cost blowouts",
      "actionTier": "tier2_warm",
      "owner": "Transgrid",
      "sector": "energy",
      "suppressed": "0",
      "discoveryStatus": "no_contacts",
      "lastDiscoveryAt": "NULL",
      "discoveryAttempts": "0"
    },
    {
      "rep_name": "Amit Bhargava",
      "project_id": "450009",
      "project_name": "MGA Thermal manufacturing capacity expansion",
      "priority": "warm",
      "location": "NSW",
      "value": "$17 million (funding)",
      "stage": "Funding secured for scaling manufacturing and commercial capability",
      "actionTier": "tier2_warm",
      "owner": "MGA Thermal",
      "sector": "energy",
      "suppressed": "0",
      "discoveryStatus": "no_contacts",
      "lastDiscoveryAt": "NULL",
      "discoveryAttempts": "0"
    },
    {
      "rep_name": "Amit Bhargava",
      "project_id": "90016",
      "project_name": "Boomer Green Energy Hub",
      "priority": "warm",
      "location": "QLD",
      "value": "1,000 MW (Wind)",
      "stage": "Proposed",
      "actionTier": "tier2_warm",
      "owner": "Ark Energy",
      "sector": "energy",
      "suppressed": "0",
      "discoveryStatus": "no_contacts",
      "lastDiscoveryAt": "NULL",
      "discoveryAttempts": "0"
    },
    {
      "rep_name": "Amit Bhargava",
      "project_id": "150048",
      "project_name": "Zelica South Gold Project Fieldwork",
      "priority": "warm",
      "location": "WA",
      "value": "Unknown",
      "stage": "Early-stage Fieldwork",
      "actionTier": "tier2_warm",
      "owner": "Strata Minerals",
      "sector": "mining",
      "suppressed": "0",
      "discoveryStatus": "no_contacts",
      "lastDiscoveryAt": "NULL",
      "discoveryAttempts": "0"
    },
    {
      "rep_name": "Amit Bhargava",
      "project_id": "480006",
      "project_name": "NT Solar and Battery Project",
      "priority": "warm",
      "location": "NT",
      "value": "Unknown",
      "stage": "Application/Approval",
      "actionTier": "tier2_warm",
      "owner": "TE H2",
      "sector": "energy",
      "suppressed": "0",
      "discoveryStatus": "send_ready_contact",
      "lastDiscoveryAt": "NULL",
      "discoveryAttempts": "0"
    },
    {
      "rep_name": "Amit Bhargava",
      "project_id": "330037",
      "project_name": "Three NSW Wind Projects (unspecified)",
      "priority": "warm",
      "location": "NSW",
      "value": "Unknown",
      "stage": "Planning/Approval - Legal Challenge Shut Down",
      "actionTier": "tier2_warm",
      "owner": "Unknown",
      "sector": "energy",
      "suppressed": "0",
      "discoveryStatus": "blocked_dirty_owner",
      "lastDiscoveryAt": "NULL",
      "discoveryAttempts": "0"
    },
    {
      "rep_name": "Amit Bhargava",
      "project_id": "120063",
      "project_name": "AGL Wind Energy Portfolio Development",
      "priority": "warm",
      "location": "NSW",
      "value": "2 gigawatt plus",
      "stage": "Planning / Funding vehicle creation",
      "actionTier": "tier2_warm",
      "owner": "AGL",
      "sector": "energy",
      "suppressed": "0",
      "discoveryStatus": "no_contacts",
      "lastDiscoveryAt": "NULL",
      "discoveryAttempts": "0"
    },
    {
      "rep_name": "Amit Bhargava",
      "project_id": "90024",
      "project_name": "Baru-Marnda Renewable Energy Project",
      "priority": "warm",
      "location": "WA",
      "value": "550 MW (Wind + Solar)",
      "stage": "Proposed",
      "actionTier": "tier2_warm",
      "owner": "Yindjibarndi Energy Corporation",
      "sector": "energy",
      "suppressed": "0",
      "discoveryStatus": "no_contacts",
      "lastDiscoveryAt": "NULL",
      "discoveryAttempts": "0"
    },
    {
      "rep_name": "Amit Bhargava",
      "project_id": "150044",
      "project_name": "NSW Safe and Secure Water Program",
      "priority": "warm",
      "location": "NSW",
      "value": "$1bn",
      "stage": "Ongoing (over 260 projects)",
      "actionTier": "tier2_warm",
      "owner": "NSW Government",
      "sector": "infrastructure",
      "suppressed": "0",
      "discoveryStatus": "blocked_government_owner",
      "lastDiscoveryAt": "NULL",
      "discoveryAttempts": "0"
    },
    {
      "rep_name": "Amit Bhargava",
      "project_id": "690044",
      "project_name": "Gorilla Gold Mines Western Australia Resource Growth",
      "priority": "warm",
      "location": "WA",
      "value": "Unknown",
      "stage": "Resource growth and near-term mine planning",
      "actionTier": "tier2_warm",
      "owner": "Gorilla Gold Mines",
      "sector": "mining",
      "suppressed": "0",
      "discoveryStatus": "no_contacts",
      "lastDiscoveryAt": "NULL",
      "discoveryAttempts": "0"
    },
    {
      "rep_name": "Amit Bhargava",
      "project_id": "120024",
      "project_name": "Hanworth Battery Energy Storage System (BESS)",
      "priority": "warm",
      "location": "NSW",
      "value": "Unknown",
      "stage": "Project sold, under development/financing by new owner",
      "actionTier": "tier2_warm",
      "owner": "Octopus Australia",
      "sector": "energy",
      "suppressed": "0",
      "discoveryStatus": "no_contacts",
      "lastDiscoveryAt": "NULL",
      "discoveryAttempts": "0"
    },
    {
      "rep_name": "Amit Bhargava",
      "project_id": "90014",
      "project_name": "Cannie Wind Farm",
      "priority": "warm",
      "location": "VIC",
      "value": "1,300 MW (Wind)",
      "stage": "Proposed",
      "actionTier": "tier2_warm",
      "owner": "RES",
      "sector": "energy",
      "suppressed": "0",
      "discoveryStatus": "no_contacts",
      "lastDiscoveryAt": "NULL",
      "discoveryAttempts": "0"
    },
    {
      "rep_name": "Amit Bhargava",
      "project_id": "90028",
      "project_name": "Moreton Hill Wind Farm",
      "priority": "warm",
      "location": "VIC",
      "value": "420 MW (Wind)",
      "stage": "Proposed",
      "actionTier": "tier2_warm",
      "owner": "Squadron Energy",
      "sector": "energy",
      "suppressed": "0",
      "discoveryStatus": "no_contacts",
      "lastDiscoveryAt": "NULL",
      "discoveryAttempts": "0"
    },
    {
      "rep_name": "Amit Bhargava",
      "project_id": "690028",
      "project_name": "Foresight's 150MWh BESS and Banpu's 1GWh BESS Development",
      "priority": "warm",
      "location": "NSW",
      "value": "Undisclosed",
      "stage": "Approved (Foresight), Federal Consideration (Banpu)",
      "actionTier": "tier2_warm",
      "owner": "Foresight, Banpu",
      "sector": "energy",
      "suppressed": "0",
      "discoveryStatus": "no_contacts",
      "lastDiscoveryAt": "NULL",
      "discoveryAttempts": "0"
    },
    {
      "rep_name": "Amit Bhargava",
      "project_id": "1020014",
      "project_name": "WAH2 Clean Ammonia Project",
      "priority": "warm",
      "location": "WA",
      "value": "A$7.3 billion GDP boost",
      "stage": "Financing bid won, FID targeted by end-2026",
      "actionTier": "tier2_warm",
      "owner": "NH3 Clean Energy",
      "sector": "energy",
      "suppressed": "0",
      "discoveryStatus": "send_ready_contact",
      "lastDiscoveryAt": "NULL",
      "discoveryAttempts": "0"
    },
    {
      "rep_name": "Amit Bhargava",
      "project_id": "120061",
      "project_name": "Hanworth BESS project",
      "priority": "warm",
      "location": "NSW",
      "value": "Unknown",
      "stage": "Acquired, planning/development",
      "actionTier": "tier2_warm",
      "owner": "Octopus Australia (acquired from Enervest)",
      "sector": "energy",
      "suppressed": "0",
      "discoveryStatus": "no_contacts",
      "lastDiscoveryAt": "NULL",
      "discoveryAttempts": "0"
    },
    {
      "rep_name": "Amit Bhargava",
      "project_id": "120084",
      "project_name": "Queensland's Hospital Rescue Plan",
      "priority": "warm",
      "location": "QLD",
      "value": "Unknown",
      "stage": "Masterplans finalised, clear timelines locked in",
      "actionTier": "tier2_warm",
      "owner": "Queensland Government",
      "sector": "infrastructure",
      "suppressed": "0",
      "discoveryStatus": "blocked_government_owner",
      "lastDiscoveryAt": "NULL",
      "discoveryAttempts": "0"
    },
    {
      "rep_name": "Amit Bhargava",
      "project_id": "300007",
      "project_name": "Burroway Solar-plus-Storage Project",
      "priority": "warm",
      "location": "NSW",
      "value": "Unknown",
      "stage": "Approved by NSW Independent Planning Commission",
      "actionTier": "tier2_warm",
      "owner": "Edify Energy",
      "sector": "energy",
      "suppressed": "0",
      "discoveryStatus": "no_contacts",
      "lastDiscoveryAt": "NULL",
      "discoveryAttempts": "0"
    },
    {
      "rep_name": "Amit Bhargava",
      "project_id": "150011",
      "project_name": "Undeveloped gold project in Northern Territory",
      "priority": "warm",
      "location": "NT",
      "value": "Unknown",
      "stage": "Ownership consolidated, clearing way for development",
      "actionTier": "tier2_warm",
      "owner": "Unknown",
      "sector": "mining",
      "suppressed": "0",
      "discoveryStatus": "blocked_dirty_owner",
      "lastDiscoveryAt": "NULL",
      "discoveryAttempts": "0"
    },
    {
      "rep_name": "Amit Bhargava",
      "project_id": "90018",
      "project_name": "Mount Rawdon Pumped Hydro",
      "priority": "warm",
      "location": "QLD",
      "value": "2,000 MW (Pumped Storage)",
      "stage": "Proposed",
      "actionTier": "tier2_warm",
      "owner": "Mt Rawdon Pumped Hydro Pty Ltd",
      "sector": "energy",
      "suppressed": "0",
      "discoveryStatus": "no_contacts",
      "lastDiscoveryAt": "NULL",
      "discoveryAttempts": "0"
    }
  ],
  "messages": [],
  "stdout": "rep_name\tproject_id\tproject_name\tpriority\tlocation\tvalue\tstage\tactionTier\towner\tsector\tsuppressed\tdiscoveryStatus\tlastDiscoveryAt\tdiscoveryAttempts\nAmit Bhargava\t120003\tRAAF Base Tindal Redevelopment Stage 6\twarm\tNT\t$1.1 billion\tActive — 0 open, 25 awarded, 2 closed work packages\ttier1_actionable\tLendlease Construction Pty Limited\tdefence\t0\tdiscovery_queued\t2026-05-03 04:04:35\t0\nAmit Bhargava\t1200024\tWA ferry infrastructure expansion\twarm\tWA\tUnknown\tApprovals secured, moving toward procurement phase\ttier1_actionable\tUnknown\tinfrastructure\t0\tno_contacts\tNULL\t0\nAmit Bhargava\t120008\tWoodside NWS Subsea Tieback Program\twarm\tWA\t$5+ billion\tActive — 0 open, 10 awarded, 1 closed work packages\ttier1_actionable\tWoodside Energy Ltd\toil_gas\t0\tsend_ready_contact\tNULL\t0\nAmit Bhargava\t30006\tNSW LDES Tender Projects (Six Projects)\twarm\tNSW\tUnknown\tContracts awarded\ttier1_actionable\tNSW Government (via ASL/AEMO Services) contracting six new battery storage projects\tenergy\t0\tdiscovery_queued\tNULL\t0\nAmit Bhargava\t270014\tQueensland road upgrade\twarm\tQLD\tUnknown\tAdvancing toward 2027 construction\ttier1_actionable\tUnknown\tinfrastructure\t0\tdiscovery_queued\tNULL\t0\nAmit Bhargava\t720010\tVictorian gas import terminal\twarm\tVIC\tUnknown\tEnvironmental approval secured, moving toward construction\ttier1_actionable\tUnknown\tenergy\t0\tdiscovery_queued\t2026-05-03 04:04:35\t0\nAmit Bhargava\t630007\tVictoria Grid Upgrades and Water Infrastructure\twarm\tVIC\tUndisclosed\tOngoing upgrades\ttier1_actionable\tVictorian Utilities (implied)\tenergy\t0\tsend_ready_contact\t2026-05-07 07:43:18\t1\nAmit Bhargava\t450010\tACT Government Open Tenders (various projects)\twarm\tACT\tUnspecified\tOpen Request for Tender (RFT)\ttier1_actionable\tACT Government\tinfrastructure\t0\tnamed_contact_no_email\t2026-05-08 01:46:52\t2\nAmit Bhargava\t120028\tEbor Battery Storage System\twarm\tNSW\t100 MW / 870 MWh\tTender awarded (Long-Term Energy Service Agreement)\ttier1_actionable\tEnergy Vault, Bridge Energy\tenergy\t0\tdiscovery_queued\tNULL\t0\nAmit Bhargava\t150019\tNew South Wales 12GWh Long Duration Energy Storage (LDES) Tender\twarm\tNSW\tUnknown\tTender process (discussion)\ttier1_actionable\tNSW Government (via tender process)\tenergy\t0\tdiscovery_queued\tNULL\t0\nAmit Bhargava\t240011\tDinawan Solar Farm\twarm\tNSW\tUnknown (part of $34 billion total for 14 projects)\tEOI endorsement / Planning\ttier1_actionable\tUnknown\tenergy\t0\tdiscovery_queued\tNULL\t0\nAmit Bhargava\t120025\tKingswood Battery Energy Storage System (BESS)\twarm\tNSW\tUnknown\tLong-term contract awarded, development ongoing\ttier1_actionable\tIberdrola Australia\tenergy\t0\tdiscovery_queued\tNULL\t0\nAmit Bhargava\t120040\tMidland Highway Lake Leake Junction Upgrade (4189)\twarm\tTAS\tUnknown\tOpen tender\ttier1_actionable\tTasmanian Government\tinfrastructure\t0\tdiscovery_queued\tNULL\t0\nAmit Bhargava\t750007\tFirst giant turbine parts for the only wind farm under construction in NSW to begin long road journey soon\twarm\tNSW\tUnknown\tConstruction (turbine delivery)\ttier1_actionable\tUnknown\tenergy\t0\tblocked_dirty_owner\t2026-05-07 07:38:16\t1\nAmit Bhargava\t450008\tACT Government Open Tenders (RFT-002)\twarm\tACT\tUnknown\tTender Open\ttier1_actionable\tACT Government\tinfrastructure\t0\tnamed_contact_no_email\t2026-05-08 01:46:54\t2\nAmit Bhargava\t120023\tNSW Long Duration Storage Tender Round 6 Projects\twarm\tNSW\tUnknown\tContracts awarded, planning/development to commence\ttier1_actionable\tVarious (awarded by NSW Government)\tenergy\t0\tdiscovery_queued\tNULL\t0\nAmit Bhargava\t120007\tChevron Australia Operations — NWS & Gorgon\twarm\tWA\t$54 billion (Gorgon project value)\tActive — 0 open, 92 awarded, 38 closed work packages\ttier1_actionable\tChevron Australia Pty Ltd\toil_gas\t0\tsend_ready_contact\tNULL\t0\nAmit Bhargava\t150009\tMajor battery storage project in Victoria\twarm\tVIC\tUnknown\tAccelerated planning approval\ttier2_warm\tUnknown\tenergy\t0\tblocked_dirty_owner\tNULL\t0\nAmit Bhargava\t270005\tAustralian Silicon Ingot and Wafer Manufacturing Facility\twarm\tQLD\tUnknown\tPlanning/Approval - Major Project Status\ttier2_warm\tUnknown\tenergy\t0\tblocked_dirty_owner\tNULL\t0\nAmit Bhargava\t120046\tTonic Group 440MWh Solar-plus-Storage Facility\twarm\tWA\tUnknown\tEnvironmental approval received\ttier2_warm\tTonic Group\tenergy\t0\tno_contacts\tNULL\t0\nAmit Bhargava\t90019\tCapricornia Energy Hub — Pumped Hydro\twarm\tQLD\t750 MW (Pumped Storage)\tProposed\ttier2_warm\tCopenhagen Infrastructure Partners\tenergy\t0\tno_contacts\tNULL\t0\nAmit Bhargava\t510017\tTransgrid 2GW Grid Battery Storage Shortlist\twarm\tNSW\tUnknown\tShortlisting/Planning\ttier2_warm\tTransgrid\tenergy\t0\tno_contacts\tNULL\t0\nAmit Bhargava\t720014\tSundown Energy Park\twarm\tQLD\tUnknown\tGrid connection approval received\ttier2_warm\tRecurrent Energy Australia\tenergy\t0\tno_contacts\tNULL\t0\nAmit Bhargava\t30007\tOctopus Australia 4.8GWh BESS Project\twarm\tNSW\tUnknown\tAcquired, planning to develop\ttier2_warm\tOctopus Australia\tenergy\t0\tno_contacts\tNULL\t0\nAmit Bhargava\t480062\tSandy Mitchell Rare Earths Project\twarm\tQLD\tUnknown\tSecured mining licence\ttier2_warm\tArk Mines\tmining\t0\tno_contacts\tNULL\t0\nAmit Bhargava\t90021\tCobbora Solar Farm\twarm\tNSW\t1,100 MW (Solar 700 + BESS 400)\tProposed\ttier2_warm\tPacific Partnerships\tenergy\t0\tno_contacts\tNULL\t0\nAmit Bhargava\t750008\tAusgrid's Energy Storage as a Service offer and network batteries\twarm\tNSW\tUnknown\tPlanning/Development (service offering)\ttier2_warm\tAusgrid\tenergy\t0\tsend_ready_contact\tNULL\t0\nAmit Bhargava\t1200052\tWA Advanced Manufacturing Facilities for Housing\twarm\tWA\t48 million AUD\tFunding Announced\ttier2_warm\tWestern Australian Government\tinfrastructure\t0\tdiscovery_queued\tNULL\t0\nAmit Bhargava\t90023\tHexham Wind Farm\twarm\tVIC\t686 MW (Wind)\tProposed\ttier2_warm\tWind Prospect Pty Ltd\tenergy\t0\tno_contacts\tNULL\t0\nAmit Bhargava\t300025\tQueensland Big Battery Project (Unnamed)\twarm\tQLD\tUnknown\tPlanning/Approval (called in by LNP)\ttier2_warm\tUnknown (LNP government called in)\tenergy\t0\tblocked_dirty_owner\tNULL\t0\nAmit Bhargava\t90022\tSpicers Creek Wind Farm\twarm\tNSW\t702 MW (Wind)\tProposed\ttier2_warm\tSquadron Energy\tenergy\t0\tno_contacts\tNULL\t0\nAmit Bhargava\t90013\tLiverpool Range Wind Farm\twarm\tNSW\t1,332 MW (Wind)\tProposed\ttier2_warm\tTilt Renewables\tenergy\t0\tno_contacts\tNULL\t0\nAmit Bhargava\t90025\tRichmond Valley Solar and BESS\twarm\tNSW\t775 MW (Solar 500 + BESS 275)\tProposed\ttier2_warm\tArk Energy\tenergy\t0\tno_contacts\tNULL\t0\nAmit Bhargava\t90027\tBashan Wind Farm\twarm\tTAS\t460 MW (Wind)\tProposed\ttier2_warm\tBashan Wind Farm Pty Ltd\tenergy\t0\tno_contacts\tNULL\t0\nAmit Bhargava\t990018\tTasmanian Transmission Infrastructure Delivery\twarm\tTAS\tUnknown\tMoving into delivery readiness following environmental approval\ttier2_warm\tUnknown\tenergy\t0\tdiscovery_queued\tNULL\t0\nAmit Bhargava\t120033\tEsmeralda Graphite Mine Project\twarm\tQLD\t$1.3 billion\tProposed project, collaboration for supply chain\ttier2_warm\tGraphinex\tmining\t0\tno_contacts\tNULL\t0\nAmit Bhargava\t90017\tBundey BESS and Solar Project\twarm\tSA\t2,100 MW (Solar 900 + BESS 1200)\tProposed\ttier2_warm\tGenaspi Energy Group\tenergy\t0\tno_contacts\tNULL\t0\nAmit Bhargava\t210001\tFederal and SA Government Housing Deal\twarm\tSA\t$801.5 million\tFunding announced\ttier2_warm\tFederal Government and South Australian Government\tinfrastructure\t0\tblocked_government_owner\tNULL\t0\nAmit Bhargava\t990032\tVan Uden Heap Leach Gold Project\twarm\tWA\tUnknown\tFeasibility Study / FID eyed for Q3 2026\ttier2_warm\tTG Metals\tmining\t0\tdiscovery_queued\tNULL\t0\nAmit Bhargava\t30011\tVictoria Government Development Facilitation Program BESS Projects\twarm\tVIC\tUnknown\tApproved\ttier2_warm\tVictoria Government\tenergy\t0\tblocked_government_owner\tNULL\t0\nAmit Bhargava\t210030\tEnergyConnect Interconnector\twarm\tNSW\tUnknown\tUnderway, facing cost blowouts\ttier2_warm\tTransgrid\tenergy\t0\tno_contacts\tNULL\t0\nAmit Bhargava\t450009\tMGA Thermal manufacturing capacity expansion\twarm\tNSW\t$17 million (funding)\tFunding secured for scaling manufacturing and commercial capability\ttier2_warm\tMGA Thermal\tenergy\t0\tno_contacts\tNULL\t0\nAmit Bhargava\t90016\tBoomer Green Energy Hub\twarm\tQLD\t1,000 MW (Wind)\tProposed\ttier2_warm\tArk Energy\tenergy\t0\tno_contacts\tNULL\t0\nAmit Bhargava\t150048\tZelica South Gold Project Fieldwork\twarm\tWA\tUnknown\tEarly-stage Fieldwork\ttier2_warm\tStrata Minerals\tmining\t0\tno_contacts\tNULL\t0\nAmit Bhargava\t480006\tNT Solar and Battery Project\twarm\tNT\tUnknown\tApplication/Approval\ttier2_warm\tTE H2\tenergy\t0\tsend_ready_contact\tNULL\t0\nAmit Bhargava\t330037\tThree NSW Wind Projects (unspecified)\twarm\tNSW\tUnknown\tPlanning/Approval - Legal Challenge Shut Down\ttier2_warm\tUnknown\tenergy\t0\tblocked_dirty_owner\tNULL\t0\nAmit Bhargava\t120063\tAGL Wind Energy Portfolio Development\twarm\tNSW\t2 gigawatt plus\tPlanning / Funding vehicle creation\ttier2_warm\tAGL\tenergy\t0\tno_contacts\tNULL\t0\nAmit Bhargava\t90024\tBaru-Marnda Renewable Energy Project\twarm\tWA\t550 MW (Wind + Solar)\tProposed\ttier2_warm\tYindjibarndi Energy Corporation\tenergy\t0\tno_contacts\tNULL\t0\nAmit Bhargava\t150044\tNSW Safe and Secure Water Program\twarm\tNSW\t$1bn\tOngoing (over 260 projects)\ttier2_warm\tNSW Government\tinfrastructure\t0\tblocked_government_owner\tNULL\t0\nAmit Bhargava\t690044\tGorilla Gold Mines Western Australia Resource Growth\twarm\tWA\tUnknown\tResource growth and near-term mine planning\ttier2_warm\tGorilla Gold Mines\tmining\t0\tno_contacts\tNULL\t0\nAmit Bhargava\t120024\tHanworth Battery Energy Storage System (BESS)\twarm\tNSW\tUnknown\tProject sold, under development/financing by new owner\ttier2_warm\tOctopus Australia\tenergy\t0\tno_contacts\tNULL\t0\nAmit Bhargava\t90014\tCannie Wind Farm\twarm\tVIC\t1,300 MW (Wind)\tProposed\ttier2_warm\tRES\tenergy\t0\tno_contacts\tNULL\t0\nAmit Bhargava\t90028\tMoreton Hill Wind Farm\twarm\tVIC\t420 MW (Wind)\tProposed\ttier2_warm\tSquadron Energy\tenergy\t0\tno_contacts\tNULL\t0\nAmit Bhargava\t690028\tForesight's 150MWh BESS and Banpu's 1GWh BESS Development\twarm\tNSW\tUndisclosed\tApproved (Foresight), Federal Consideration (Banpu)\ttier2_warm\tForesight, Banpu\tenergy\t0\tno_contacts\tNULL\t0\nAmit Bhargava\t1020014\tWAH2 Clean Ammonia Project\twarm\tWA\tA$7.3 billion GDP boost\tFinancing bid won, FID targeted by end-2026\ttier2_warm\tNH3 Clean Energy\tenergy\t0\tsend_ready_contact\tNULL\t0\nAmit Bhargava\t120061\tHanworth BESS project\twarm\tNSW\tUnknown\tAcquired, planning/development\ttier2_warm\tOctopus Australia (acquired from Enervest)\tenergy\t0\tno_contacts\tNULL\t0\nAmit Bhargava\t120084\tQueensland's Hospital Rescue Plan\twarm\tQLD\tUnknown\tMasterplans finalised, clear timelines locked in\ttier2_warm\tQueensland Government\tinfrastructure\t0\tblocked_government_owner\tNULL\t0\nAmit Bhargava\t300007\tBurroway Solar-plus-Storage Project\twarm\tNSW\tUnknown\tApproved by NSW Independent Planning Commission\ttier2_warm\tEdify Energy\tenergy\t0\tno_contacts\tNULL\t0\nAmit Bhargava\t150011\tUndeveloped gold project in Northern Territory\twarm\tNT\tUnknown\tOwnership consolidated, clearing way for development\ttier2_warm\tUnknown\tmining\t0\tblocked_dirty_owner\tNULL\t0\nAmit Bhargava\t90018\tMount Rawdon Pumped Hydro\twarm\tQLD\t2,000 MW (Pumped Storage)\tProposed\ttier2_warm\tMt Rawdon Pumped Hydro Pty Ltd\tenergy\t0\tno_contacts\tNULL\t0\n",
  "stderr": "",
  "execution_time_ms": 1779
}